today_in_history/__init__.py
today_in_history/cli.py
today_in_history/utils.py
today_in_history-0.1.0.dist-info/METADATA
today_in_history-0.1.0.dist-info/WHEEL
today_in_history-0.1.0.dist-info/entry_points.txt
today_in_history-0.1.0.dist-info/RECORD
